pyroma/__init__.py
pyroma/plotting.py
pyroma/roma.py
pyroma/sparse_methods.py
pyroma/sparse_methods_old.py
pyroma/test_pyroma.py
pyroma/utils.py
pyroma/datasets/__init__.py
pyroma/datasets/kang_tutorial.h5ad
pyroma/datasets/rna_10xpmbc3k.h5ad
pyroma/datasets/from_R/rheman-cf-ncf-rna-exp-matrix-norm-sample_labels.tsv
pyroma/datasets/from_R/rheman-cf-ncf-rna-exp-matrix-norm.tsv
pyroma/datasets/from_R/rheman-il17-tnf-rna-exp-matrix-norm-sample_labels.tsv
pyroma/datasets/from_R/rheman-il17-tnf-rna-exp-matrix-norm.tsv
pyroma/genesets/ReactomePathways.gmt
pyroma/genesets/__init__.py
pyroma/genesets/h.all.v2023.1.Hs.symbols.gmt
pyroma/genesets/progeny_p.gmt
pyroma/genesets/msigdb_v2023.2.Hs_GMTs/._c1.all.v2023.2.Hs.entrez.gmt
pyroma/genesets/msigdb_v2023.2.Hs_GMTs/._c1.all.v2023.2.Hs.symbols.gmt
pyroma/genesets/msigdb_v2023.2.Hs_GMTs/._c2.all.v2023.2.Hs.entrez.gmt
pyroma/genesets/msigdb_v2023.2.Hs_GMTs/._c2.all.v2023.2.Hs.symbols.gmt
pyroma/genesets/msigdb_v2023.2.Hs_GMTs/._c2.cgp.v2023.2.Hs.entrez.gmt
pyroma/genesets/msigdb_v2023.2.Hs_GMTs/._c2.cgp.v2023.2.Hs.symbols.gmt
pyroma/genesets/msigdb_v2023.2.Hs_GMTs/._c2.cp.biocarta.v2023.2.Hs.entrez.gmt
pyroma/genesets/msigdb_v2023.2.Hs_GMTs/._c2.cp.biocarta.v2023.2.Hs.symbols.gmt
pyroma/genesets/msigdb_v2023.2.Hs_GMTs/._c2.cp.kegg_legacy.v2023.2.Hs.entrez.gmt
pyroma/genesets/msigdb_v2023.2.Hs_GMTs/._c2.cp.kegg_legacy.v2023.2.Hs.symbols.gmt
pyroma/genesets/msigdb_v2023.2.Hs_GMTs/._c2.cp.kegg_medicus.v2023.2.Hs.entrez.gmt
pyroma/genesets/msigdb_v2023.2.Hs_GMTs/._c2.cp.kegg_medicus.v2023.2.Hs.symbols.gmt
pyroma/genesets/msigdb_v2023.2.Hs_GMTs/._c2.cp.pid.v2023.2.Hs.entrez.gmt
pyroma/genesets/msigdb_v2023.2.Hs_GMTs/._c2.cp.pid.v2023.2.Hs.symbols.gmt
pyroma/genesets/msigdb_v2023.2.Hs_GMTs/._c2.cp.reactome.v2023.2.Hs.entrez.gmt
pyroma/genesets/msigdb_v2023.2.Hs_GMTs/._c2.cp.reactome.v2023.2.Hs.symbols.gmt
pyroma/genesets/msigdb_v2023.2.Hs_GMTs/._c2.cp.v2023.2.Hs.entrez.gmt
roma_analysis-0.2.3.dist-info/METADATA
roma_analysis-0.2.3.dist-info/WHEEL
roma_analysis-0.2.3.dist-info/top_level.txt
roma_analysis-0.2.3.dist-info/RECORD
