Metadata-Version: 2.1
Name: roma-analysis
Version: 0.2.3
Summary: Representation and Quantification of Module Activity for bulk and single cell transcriptomics in python
Home-page: https://github.com/altyn-bulmers
Download-URL: https://github.com/altyn-bulmers/pyroma/archive/refs/tags/0.2.3.tar.gz
Author: Altynbek Zhubanchaliyev
Author-email: altynbek.zhubanchaliyev@curie.fr
License: GPL-3.0
Keywords: python,bioinformatics,machine-learning,pathway-activity,transcriptomics,rna-seq-analysis,single-cell-rna-seq,pathway-analysis,pathway-enrichment-analysis
Classifier: Development Status :: 3 - Alpha
Classifier: License :: OSI Approved :: GNU General Public License v3 (GPLv3)
Classifier: Programming Language :: Python :: 3
Requires-Python: >=3.7
Requires-Dist: scanpy
Requires-Dist: scikit-learn
Requires-Dist: numpy
Requires-Dist: matplotlib
Requires-Dist: pandas
